{
    "Sum_Trips_per_Mode": {
        "work": {
            "60101": {
                "car": 81.89054215575491,
                "publicTransport": 1326.1489014223548
            },
            "60669": {
                "car": 4.204243139776057,
                "publicTransport": 54.15111480612738
            },
            "60608": {
                "car": 1.7972234903762185,
                "publicTransport": 26.390726331402142
            },
            "60611": {
                "car": 4.0546605132434355,
                "publicTransport": 15.242520628054688
            },
            "60670": {
                "car": 4.391864690180614,
                "publicTransport": 45.914041073646445
            },
            "60662": {
                "car": 3.400211034231751,
                "publicTransport": 12.290993898383725
            },
            "60656": {
                "car": 1.2059248874668032,
                "publicTransport": 11.015349287677306
            },
            "60655": {
                "car": 1.571300742574691,
                "publicTransport": 18.599405942183065
            },
            "60624": {
                "car": 3.234121711563395,
                "publicTransport": 41.2583680625622
            },
            "60660": {
                "car": 1.4989365113032687,
                "publicTransport": 11.573082400872936
            },
            "60629": {
                "car": 2.77648774639046,
                "publicTransport": 17.32529164241374
            },
            "60618": {
                "car": 0.49043293443825986,
                "publicTransport": 4.171320976372193
            },
            "61059": {
                "car": 2.0014183773968464,
                "publicTransport": 20.205866837703603
            },
            "61001": {
                "car": 1.2601018997156639,
                "publicTransport": 4.150669558343652
            },
            "61055": {
                "car": 1.8440065159665617,
                "publicTransport": 5.656391012813341
            },
            "61021": {
                "car": 7.29822866511938,
                "publicTransport": 23.211759524289434
            },
            "61017": {
                "car": 0.7320334958349228,
                "publicTransport": 3.1090237125250093
            },
            "61020": {
                "car": 1.3200267350300026,
                "publicTransport": 5.722252535702999
            },
            "61012": {
                "car": 2.238909075044667,
                "publicTransport": 13.518510802253942
            },
            "61043": {
                "car": 2.7652736983389223,
                "publicTransport": 13.205913290662078
            },
            "61053": {
                "car": 16.830025125276656,
                "publicTransport": 112.65949424934979
            },
            "61027": {
                "car": 2.5831398168433646,
                "publicTransport": 7.579829719266419
            },
            "61016": {
                "car": 1.2099752587499992,
                "publicTransport": 5.485403285713685
            },
            "61045": {
                "car": 11.387959058688944,
                "publicTransport": 30.785671504579234
            },
            "61008": {
                "car": 1.9701470648672008,
                "publicTransport": 11.80354503945807
            },
            "61050": {
                "car": 4.954606033764456,
                "publicTransport": 15.286015694994346
            },
            "61049": {
                "car": 3.8717825804152426,
                "publicTransport": 11.971271871000514
            },
            "61058": {
                "car": 10.291288857948945,
                "publicTransport": 30.19454801748928
            },
            "62347": {
                "car": 1.2260133376294848,
                "publicTransport": 3.761356460297197
            }
        }
    },
    "Trips_per_group": {
        "work": {
            "60101": {
                "car": {
                    "popGroup2": 39.02182449200883,
                    "popGroup4": 0.0,
                    "popGroup6": 0.0,
                    "popGroup10": 42.86871766374608,
                    "popGroup12": 0.0,
                    "popGroup14": 0.0
                },
                "publicTransport": {
                    "popGroup0": 0.0,
                    "popGroup1": 0.0,
                    "popGroup2": 102.04105388538905,
                    "popGroup3": 577.7037783970384,
                    "popGroup4": 0.0,
                    "popGroup5": 0.0,
                    "popGroup6": 0.0,
                    "popGroup7": 0.0,
                    "popGroup8": 0.0,
                    "popGroup9": 0.0,
                    "popGroup10": 112.33396684211405,
                    "popGroup11": 534.0701022978133,
                    "popGroup12": 0.0,
                    "popGroup13": 0.0,
                    "popGroup14": 0.0,
                    "popGroup15": 0.0
                }
            },
            "60669": {
                "car": {
                    "popGroup2": 2.002765982294848,
                    "popGroup4": 0.0,
                    "popGroup6": 0.0,
                    "popGroup10": 2.201477157481209,
                    "popGroup12": 0.0,
                    "popGroup14": 0.0
                },
                "publicTransport": {
                    "popGroup0": 0.0,
                    "popGroup1": 0.0,
                    "popGroup2": 4.166939471264446,
                    "popGroup3": 23.590114325549003,
                    "popGroup4": 0.0,
                    "popGroup5": 0.0,
                    "popGroup6": 0.0,
                    "popGroup7": 0.0,
                    "popGroup8": 0.0,
                    "popGroup9": 0.0,
                    "popGroup10": 4.58653016720507,
                    "popGroup11": 21.807530842108857,
                    "popGroup12": 0.0,
                    "popGroup13": 0.0,
                    "popGroup14": 0.0,
                    "popGroup15": 0.0
                }
            },
            "60608": {
                "car": {
                    "popGroup2": 0.8561876005314885,
                    "popGroup4": 0.0,
                    "popGroup6": 0.0,
                    "popGroup10": 0.94103588984473,
                    "popGroup12": 0.0,
                    "popGroup14": 0.0
                },
                "publicTransport": {
                    "popGroup0": 0.0,
                    "popGroup1": 0.0,
                    "popGroup2": 2.0308416215742873,
                    "popGroup3": 11.496862383950072,
                    "popGroup4": 0.0,
                    "popGroup5": 0.0,
                    "popGroup6": 0.0,
                    "popGroup7": 0.0,
                    "popGroup8": 0.0,
                    "popGroup9": 0.0,
                    "popGroup10": 2.2351420756739864,
                    "popGroup11": 10.627880250203797,
                    "popGroup12": 0.0,
                    "popGroup13": 0.0,
                    "popGroup14": 0.0,
                    "popGroup15": 0.0
                }
            },
            "60611": {
                "car": {
                    "popGroup2": 1.9303425084821324,
                    "popGroup4": 0.0,
                    "popGroup6": 0.0,
                    "popGroup10": 2.1243180047613035,
                    "popGroup12": 0.0,
                    "popGroup14": 0.0
                },
                "publicTransport": {
                    "popGroup0": 0.0,
                    "popGroup1": 0.0,
                    "popGroup2": 1.1729785828938684,
                    "popGroup3": 6.640302351921133,
                    "popGroup4": 0.0,
                    "popGroup5": 0.0,
                    "popGroup6": 0.0,
                    "popGroup7": 0.0,
                    "popGroup8": 0.0,
                    "popGroup9": 0.0,
                    "popGroup10": 1.2909140415872475,
                    "popGroup11": 6.138325651652439,
                    "popGroup12": 0.0,
                    "popGroup13": 0.0,
                    "popGroup14": 0.0,
                    "popGroup15": 0.0
                }
            },
            "60670": {
                "car": {
                    "popGroup2": 2.091681072063735,
                    "popGroup4": 0.0,
                    "popGroup6": 0.0,
                    "popGroup10": 2.300183618116879,
                    "popGroup12": 0.0,
                    "popGroup14": 0.0
                },
                "publicTransport": {
                    "popGroup0": 0.0,
                    "popGroup1": 0.0,
                    "popGroup2": 3.533216344867401,
                    "popGroup3": 20.002003926911193,
                    "popGroup4": 0.0,
                    "popGroup5": 0.0,
                    "popGroup6": 0.0,
                    "popGroup7": 0.0,
                    "popGroup8": 0.0,
                    "popGroup9": 0.0,
                    "popGroup10": 3.8886540589759617,
                    "popGroup11": 18.490166742891883,
                    "popGroup12": 0.0,
                    "popGroup13": 0.0,
                    "popGroup14": 0.0,
                    "popGroup15": 0.0
                }
            },
            "60662": {
                "car": {
                    "popGroup2": 1.6188701635999685,
                    "popGroup4": 0.0,
                    "popGroup6": 0.0,
                    "popGroup10": 1.7813408706317824,
                    "popGroup12": 0.0,
                    "popGroup14": 0.0
                },
                "publicTransport": {
                    "popGroup0": 0.0,
                    "popGroup1": 0.0,
                    "popGroup2": 0.94591027992786,
                    "popGroup3": 5.354620407097728,
                    "popGroup4": 0.0,
                    "popGroup5": 0.0,
                    "popGroup6": 0.0,
                    "popGroup7": 0.0,
                    "popGroup8": 0.0,
                    "popGroup9": 0.0,
                    "popGroup10": 1.0408345679709248,
                    "popGroup11": 4.949628643387213,
                    "popGroup12": 0.0,
                    "popGroup13": 0.0,
                    "popGroup14": 0.0,
                    "popGroup15": 0.0
                }
            },
            "60656": {
                "car": {
                    "popGroup2": 0.5742871182760994,
                    "popGroup4": 0.0,
                    "popGroup6": 0.0,
                    "popGroup10": 0.6316377691907039,
                    "popGroup12": 0.0,
                    "popGroup14": 0.0
                },
                "publicTransport": {
                    "popGroup0": 0.0,
                    "popGroup1": 0.0,
                    "popGroup2": 0.8477222794441044,
                    "popGroup3": 4.798850601013754,
                    "popGroup4": 0.0,
                    "popGroup5": 0.0,
                    "popGroup6": 0.0,
                    "popGroup7": 0.0,
                    "popGroup8": 0.0,
                    "popGroup9": 0.0,
                    "popGroup10": 0.9328348247644052,
                    "popGroup11": 4.435941582455044,
                    "popGroup12": 0.0,
                    "popGroup13": 0.0,
                    "popGroup14": 0.0,
                    "popGroup15": 0.0
                }
            },
            "60655": {
                "car": {
                    "popGroup2": 0.7483642074250404,
                    "popGroup4": 0.0,
                    "popGroup6": 0.0,
                    "popGroup10": 0.8229365351496507,
                    "popGroup12": 0.0,
                    "popGroup14": 0.0
                },
                "publicTransport": {
                    "popGroup0": 0.0,
                    "popGroup1": 0.0,
                    "popGroup2": 1.4314192435504633,
                    "popGroup3": 8.102937544395148,
                    "popGroup4": 0.0,
                    "popGroup5": 0.0,
                    "popGroup6": 0.0,
                    "popGroup7": 0.0,
                    "popGroup8": 0.0,
                    "popGroup9": 0.0,
                    "popGroup10": 1.5750208334990219,
                    "popGroup11": 7.490028320738432,
                    "popGroup12": 0.0,
                    "popGroup13": 0.0,
                    "popGroup14": 0.0,
                    "popGroup15": 0.0
                }
            },
            "60624": {
                "car": {
                    "popGroup2": 1.540431582216646,
                    "popGroup4": 0.0,
                    "popGroup6": 0.0,
                    "popGroup10": 1.693690129346749,
                    "popGroup12": 0.0,
                    "popGroup14": 0.0
                },
                "publicTransport": {
                    "popGroup0": 0.0,
                    "popGroup1": 0.0,
                    "popGroup2": 3.17513447034647,
                    "popGroup3": 17.97418149513015,
                    "popGroup4": 0.0,
                    "popGroup5": 0.0,
                    "popGroup6": 0.0,
                    "popGroup7": 0.0,
                    "popGroup8": 0.0,
                    "popGroup9": 0.0,
                    "popGroup10": 3.494030039919388,
                    "popGroup11": 16.61502205716619,
                    "popGroup12": 0.0,
                    "popGroup13": 0.0,
                    "popGroup14": 0.0,
                    "popGroup15": 0.0
                }
            },
            "60660": {
                "car": {
                    "popGroup2": 0.7137957258048343,
                    "popGroup4": 0.0,
                    "popGroup6": 0.0,
                    "popGroup10": 0.7851407854984342,
                    "popGroup12": 0.0,
                    "popGroup14": 0.0
                },
                "publicTransport": {
                    "popGroup0": 0.0,
                    "popGroup1": 0.0,
                    "popGroup2": 0.8906059179084558,
                    "popGroup3": 5.041749564454734,
                    "popGroup4": 0.0,
                    "popGroup5": 0.0,
                    "popGroup6": 0.0,
                    "popGroup7": 0.0,
                    "popGroup8": 0.0,
                    "popGroup9": 0.0,
                    "popGroup10": 0.9801320014366129,
                    "popGroup11": 4.660594917073134,
                    "popGroup12": 0.0,
                    "popGroup13": 0.0,
                    "popGroup14": 0.0,
                    "popGroup15": 0.0
                }
            },
            "60629": {
                "car": {
                    "popGroup2": 1.3220656151605021,
                    "popGroup4": 0.0,
                    "popGroup6": 0.0,
                    "popGroup10": 1.4544221312299577,
                    "popGroup12": 0.0,
                    "popGroup14": 0.0
                },
                "publicTransport": {
                    "popGroup0": 0.0,
                    "popGroup1": 0.0,
                    "popGroup2": 1.3331440811457234,
                    "popGroup3": 7.5474187877668975,
                    "popGroup4": 0.0,
                    "popGroup5": 0.0,
                    "popGroup6": 0.0,
                    "popGroup7": 0.0,
                    "popGroup8": 0.0,
                    "popGroup9": 0.0,
                    "popGroup10": 1.4674992670633582,
                    "popGroup11": 6.977229506437762,
                    "popGroup12": 0.0,
                    "popGroup13": 0.0,
                    "popGroup14": 0.0,
                    "popGroup15": 0.0
                }
            },
            "60618": {
                "car": {
                    "popGroup2": 0.23355055465701466,
                    "popGroup4": 0.0,
                    "popGroup6": 0.0,
                    "popGroup10": 0.25688237978124523,
                    "popGroup12": 0.0,
                    "popGroup14": 0.0
                },
                "publicTransport": {
                    "popGroup0": 0.0,
                    "popGroup1": 0.0,
                    "popGroup2": 0.3209639491211914,
                    "popGroup3": 1.817132213714789,
                    "popGroup4": 0.0,
                    "popGroup5": 0.0,
                    "popGroup6": 0.0,
                    "popGroup7": 0.0,
                    "popGroup8": 0.0,
                    "popGroup9": 0.0,
                    "popGroup10": 0.3533396828553976,
                    "popGroup11": 1.6798851306808147,
                    "popGroup12": 0.0,
                    "popGroup13": 0.0,
                    "popGroup14": 0.0,
                    "popGroup15": 0.0
                }
            },
            "61059": {
                "car": {
                    "popGroup2": 0.9531554984439465,
                    "popGroup4": 0.0,
                    "popGroup6": 0.0,
                    "popGroup10": 1.0482628789528996,
                    "popGroup12": 0.0,
                    "popGroup14": 0.0
                },
                "publicTransport": {
                    "popGroup0": 0.0,
                    "popGroup1": 0.0,
                    "popGroup2": 1.555152299762684,
                    "popGroup3": 8.803002285971267,
                    "popGroup4": 0.0,
                    "popGroup5": 0.0,
                    "popGroup6": 0.0,
                    "popGroup7": 0.0,
                    "popGroup8": 0.0,
                    "popGroup9": 0.0,
                    "popGroup10": 1.7108894878085925,
                    "popGroup11": 8.136822764161058,
                    "popGroup12": 0.0,
                    "popGroup13": 0.0,
                    "popGroup14": 0.0,
                    "popGroup15": 0.0
                }
            },
            "61001": {
                "car": {
                    "popGroup2": 0.5999909407118932,
                    "popGroup4": 0.0,
                    "popGroup6": 0.0,
                    "popGroup10": 0.6601109590037708,
                    "popGroup12": 0.0,
                    "popGroup14": 0.0
                },
                "publicTransport": {
                    "popGroup0": 0.0,
                    "popGroup1": 0.0,
                    "popGroup2": 0.3194578763217612,
                    "popGroup3": 1.808304187288364,
                    "popGroup4": 0.0,
                    "popGroup5": 0.0,
                    "popGroup6": 0.0,
                    "popGroup7": 0.0,
                    "popGroup8": 0.0,
                    "popGroup9": 0.0,
                    "popGroup10": 0.35144925836521806,
                    "popGroup11": 1.6714582363683084,
                    "popGroup12": 0.0,
                    "popGroup13": 0.0,
                    "popGroup14": 0.0,
                    "popGroup15": 0.0
                }
            },
            "61055": {
                "car": {
                    "popGroup2": 0.8780627058001165,
                    "popGroup4": 0.0,
                    "popGroup6": 0.0,
                    "popGroup10": 0.9659438101664453,
                    "popGroup12": 0.0,
                    "popGroup14": 0.0
                },
                "publicTransport": {
                    "popGroup0": 0.0,
                    "popGroup1": 0.0,
                    "popGroup2": 0.4353646377624958,
                    "popGroup3": 2.4643324900324317,
                    "popGroup4": 0.0,
                    "popGroup5": 0.0,
                    "popGroup6": 0.0,
                    "popGroup7": 0.0,
                    "popGroup8": 0.0,
                    "popGroup9": 0.0,
                    "popGroup10": 0.47891189719758404,
                    "popGroup11": 2.2777819878208296,
                    "popGroup12": 0.0,
                    "popGroup13": 0.0,
                    "popGroup14": 0.0,
                    "popGroup15": 0.0
                }
            },
            "61021": {
                "car": {
                    "popGroup2": 3.4751426465593696,
                    "popGroup4": 0.0,
                    "popGroup6": 0.0,
                    "popGroup10": 3.8230860185600104,
                    "popGroup12": 0.0,
                    "popGroup14": 0.0
                },
                "publicTransport": {
                    "popGroup0": 0.0,
                    "popGroup1": 0.0,
                    "popGroup2": 1.7865529087858294,
                    "popGroup3": 10.112669769342224,
                    "popGroup4": 0.0,
                    "popGroup5": 0.0,
                    "popGroup6": 0.0,
                    "popGroup7": 0.0,
                    "popGroup8": 0.0,
                    "popGroup9": 0.0,
                    "popGroup10": 1.9653205600552324,
                    "popGroup11": 9.347216286106148,
                    "popGroup12": 0.0,
                    "popGroup13": 0.0,
                    "popGroup14": 0.0,
                    "popGroup15": 0.0
                }
            },
            "61017": {
                "car": {
                    "popGroup2": 0.34854213439470605,
                    "popGroup4": 0.0,
                    "popGroup6": 0.0,
                    "popGroup10": 0.3834913614402168,
                    "popGroup12": 0.0,
                    "popGroup14": 0.0
                },
                "publicTransport": {
                    "popGroup0": 0.0,
                    "popGroup1": 0.0,
                    "popGroup2": 0.23927196301844111,
                    "popGroup3": 1.3544639568029564,
                    "popGroup4": 0.0,
                    "popGroup5": 0.0,
                    "popGroup6": 0.0,
                    "popGroup7": 0.0,
                    "popGroup8": 0.0,
                    "popGroup9": 0.0,
                    "popGroup10": 0.26327599571143157,
                    "popGroup11": 1.2520117969921805,
                    "popGroup12": 0.0,
                    "popGroup13": 0.0,
                    "popGroup14": 0.0,
                    "popGroup15": 0.0
                }
            },
            "61020": {
                "car": {
                    "popGroup2": 0.6285532544098906,
                    "popGroup4": 0.0,
                    "popGroup6": 0.0,
                    "popGroup10": 0.6914734806201118,
                    "popGroup12": 0.0,
                    "popGroup14": 0.0
                },
                "publicTransport": {
                    "popGroup0": 0.0,
                    "popGroup1": 0.0,
                    "popGroup2": 0.44042026382385513,
                    "popGroup3": 2.492998857571883,
                    "popGroup4": 0.0,
                    "popGroup5": 0.0,
                    "popGroup6": 0.0,
                    "popGroup7": 0.0,
                    "popGroup8": 0.0,
                    "popGroup9": 0.0,
                    "popGroup10": 0.48451142432182126,
                    "popGroup11": 2.30432198998544,
                    "popGroup12": 0.0,
                    "popGroup13": 0.0,
                    "popGroup14": 0.0,
                    "popGroup15": 0.0
                }
            },
            "61012": {
                "car": {
                    "popGroup2": 1.0661658262793219,
                    "popGroup4": 0.0,
                    "popGroup6": 0.0,
                    "popGroup10": 1.172743248765345,
                    "popGroup12": 0.0,
                    "popGroup14": 0.0
                },
                "publicTransport": {
                    "popGroup0": 0.0,
                    "popGroup1": 0.0,
                    "popGroup2": 1.0405153695101559,
                    "popGroup3": 5.889668518167143,
                    "popGroup4": 0.0,
                    "popGroup5": 0.0,
                    "popGroup6": 0.0,
                    "popGroup7": 0.0,
                    "popGroup8": 0.0,
                    "popGroup9": 0.0,
                    "popGroup10": 1.1445529858055499,
                    "popGroup11": 5.443773928771094,
                    "popGroup12": 0.0,
                    "popGroup13": 0.0,
                    "popGroup14": 0.0,
                    "popGroup15": 0.0
                }
            },
            "61043": {
                "car": {
                    "popGroup2": 1.3167807406819103,
                    "popGroup4": 0.0,
                    "popGroup6": 0.0,
                    "popGroup10": 1.4484929576570122,
                    "popGroup12": 0.0,
                    "popGroup14": 0.0
                },
                "publicTransport": {
                    "popGroup0": 0.0,
                    "popGroup1": 0.0,
                    "popGroup2": 1.0164362698136329,
                    "popGroup3": 5.753440138674184,
                    "popGroup4": 0.0,
                    "popGroup5": 0.0,
                    "popGroup6": 0.0,
                    "popGroup7": 0.0,
                    "popGroup8": 0.0,
                    "popGroup9": 0.0,
                    "popGroup10": 1.1181183078367454,
                    "popGroup11": 5.317918574337518,
                    "popGroup12": 0.0,
                    "popGroup13": 0.0,
                    "popGroup14": 0.0,
                    "popGroup15": 0.0
                }
            },
            "61053": {
                "car": {
                    "popGroup2": 8.014568500439198,
                    "popGroup4": 0.0,
                    "popGroup6": 0.0,
                    "popGroup10": 8.81545662483746,
                    "popGroup12": 0.0,
                    "popGroup14": 0.0
                },
                "publicTransport": {
                    "popGroup0": 0.0,
                    "popGroup1": 0.0,
                    "popGroup2": 8.67149044162719,
                    "popGroup3": 49.083108153516804,
                    "popGroup4": 0.0,
                    "popGroup5": 0.0,
                    "popGroup6": 0.0,
                    "popGroup7": 0.0,
                    "popGroup8": 0.0,
                    "popGroup9": 0.0,
                    "popGroup10": 9.538170894387822,
                    "popGroup11": 45.36672475981798,
                    "popGroup12": 0.0,
                    "popGroup13": 0.0,
                    "popGroup14": 0.0,
                    "popGroup15": 0.0
                }
            },
            "61027": {
                "car": {
                    "popGroup2": 1.2300605548913148,
                    "popGroup4": 0.0,
                    "popGroup6": 0.0,
                    "popGroup10": 1.3530792619520495,
                    "popGroup12": 0.0,
                    "popGroup14": 0.0
                },
                "publicTransport": {
                    "popGroup0": 0.0,
                    "popGroup1": 0.0,
                    "popGroup2": 0.5834220114084723,
                    "popGroup3": 3.3023475650800345,
                    "popGroup4": 0.0,
                    "popGroup5": 0.0,
                    "popGroup6": 0.0,
                    "popGroup7": 0.0,
                    "popGroup8": 0.0,
                    "popGroup9": 0.0,
                    "popGroup10": 0.6417424356275565,
                    "popGroup11": 3.052317707150357,
                    "popGroup12": 0.0,
                    "popGroup13": 0.0,
                    "popGroup14": 0.0,
                    "popGroup15": 0.0
                }
            },
            "61016": {
                "car": {
                    "popGroup2": 0.5761558314775844,
                    "popGroup4": 0.0,
                    "popGroup6": 0.0,
                    "popGroup10": 0.6338194272724148,
                    "popGroup12": 0.0,
                    "popGroup14": 0.0
                },
                "publicTransport": {
                    "popGroup0": 0.0,
                    "popGroup1": 0.0,
                    "popGroup2": 0.42219296086532704,
                    "popGroup3": 2.389815606448944,
                    "popGroup4": 0.0,
                    "popGroup5": 0.0,
                    "popGroup6": 0.0,
                    "popGroup7": 0.0,
                    "popGroup8": 0.0,
                    "popGroup9": 0.0,
                    "popGroup10": 0.4644534951314952,
                    "popGroup11": 2.208941223267919,
                    "popGroup12": 0.0,
                    "popGroup13": 0.0,
                    "popGroup14": 0.0,
                    "popGroup15": 0.0
                }
            },
            "61045": {
                "car": {
                    "popGroup2": 5.422999192904083,
                    "popGroup4": 0.0,
                    "popGroup6": 0.0,
                    "popGroup10": 5.964959865784861,
                    "popGroup12": 0.0,
                    "popGroup14": 0.0
                },
                "publicTransport": {
                    "popGroup0": 0.0,
                    "popGroup1": 0.0,
                    "popGroup2": 2.369627968825586,
                    "popGroup3": 13.412659221491085,
                    "popGroup4": 0.0,
                    "popGroup5": 0.0,
                    "popGroup6": 0.0,
                    "popGroup7": 0.0,
                    "popGroup8": 0.0,
                    "popGroup9": 0.0,
                    "popGroup10": 2.606377391527797,
                    "popGroup11": 12.39700692273477,
                    "popGroup12": 0.0,
                    "popGroup13": 0.0,
                    "popGroup14": 0.0,
                    "popGroup15": 0.0
                }
            },
            "61008": {
                "car": {
                    "popGroup2": 0.9382160899733453,
                    "popGroup4": 0.0,
                    "popGroup6": 0.0,
                    "popGroup10": 1.0319309748938554,
                    "popGroup12": 0.0,
                    "popGroup14": 0.0
                },
                "publicTransport": {
                    "popGroup0": 0.0,
                    "popGroup1": 0.0,
                    "popGroup2": 0.9085469006223059,
                    "popGroup3": 5.142566572700708,
                    "popGroup4": 0.0,
                    "popGroup5": 0.0,
                    "popGroup6": 0.0,
                    "popGroup7": 0.0,
                    "popGroup8": 0.0,
                    "popGroup9": 0.0,
                    "popGroup10": 0.9993001329483189,
                    "popGroup11": 4.753131433186738,
                    "popGroup12": 0.0,
                    "popGroup13": 0.0,
                    "popGroup14": 0.0,
                    "popGroup15": 0.0
                }
            },
            "61050": {
                "car": {
                    "popGroup2": 2.359225007169004,
                    "popGroup4": 0.0,
                    "popGroup6": 0.0,
                    "popGroup10": 2.595381026595452,
                    "popGroup12": 0.0,
                    "popGroup14": 0.0
                },
                "publicTransport": {
                    "popGroup0": 0.0,
                    "popGroup1": 0.0,
                    "popGroup2": 1.176538148582205,
                    "popGroup3": 6.659681486942036,
                    "popGroup4": 0.0,
                    "popGroup5": 0.0,
                    "popGroup6": 0.0,
                    "popGroup7": 0.0,
                    "popGroup8": 0.0,
                    "popGroup9": 0.0,
                    "popGroup10": 1.294236424718803,
                    "popGroup11": 6.155559634751301,
                    "popGroup12": 0.0,
                    "popGroup13": 0.0,
                    "popGroup14": 0.0,
                    "popGroup15": 0.0
                }
            },
            "61049": {
                "car": {
                    "popGroup2": 1.843652649919443,
                    "popGroup4": 0.0,
                    "popGroup6": 0.0,
                    "popGroup10": 2.0281299304957994,
                    "popGroup12": 0.0,
                    "popGroup14": 0.0
                },
                "publicTransport": {
                    "popGroup0": 0.0,
                    "popGroup1": 0.0,
                    "popGroup2": 0.9214181218961404,
                    "popGroup3": 5.215562458061958,
                    "popGroup4": 0.0,
                    "popGroup5": 0.0,
                    "popGroup6": 0.0,
                    "popGroup7": 0.0,
                    "popGroup8": 0.0,
                    "popGroup9": 0.0,
                    "popGroup10": 1.0135665709931265,
                    "popGroup11": 4.820724720049288,
                    "popGroup12": 0.0,
                    "popGroup13": 0.0,
                    "popGroup14": 0.0,
                    "popGroup15": 0.0
                }
            },
            "61058": {
                "car": {
                    "popGroup2": 4.900589697320024,
                    "popGroup4": 0.0,
                    "popGroup6": 0.0,
                    "popGroup10": 5.390699160628921,
                    "popGroup12": 0.0,
                    "popGroup14": 0.0
                },
                "publicTransport": {
                    "popGroup0": 0.0,
                    "popGroup1": 0.0,
                    "popGroup2": 2.3240843911251075,
                    "popGroup3": 13.155030629619233,
                    "popGroup4": 0.0,
                    "popGroup5": 0.0,
                    "popGroup6": 0.0,
                    "popGroup7": 0.0,
                    "popGroup8": 0.0,
                    "popGroup9": 0.0,
                    "popGroup10": 2.556406081018414,
                    "popGroup11": 12.159026915726525,
                    "popGroup12": 0.0,
                    "popGroup13": 0.0,
                    "popGroup14": 0.0,
                    "popGroup15": 0.0
                }
            },
            "62347": {
                "car": {
                    "popGroup2": 0.5837921941871449,
                    "popGroup4": 0.0,
                    "popGroup6": 0.0,
                    "popGroup10": 0.6422211434423398,
                    "popGroup12": 0.0,
                    "popGroup14": 0.0
                },
                "publicTransport": {
                    "popGroup0": 0.0,
                    "popGroup1": 0.0,
                    "popGroup2": 0.28950643424815714,
                    "popGroup3": 1.6387185593616678,
                    "popGroup4": 0.0,
                    "popGroup5": 0.0,
                    "popGroup6": 0.0,
                    "popGroup7": 0.0,
                    "popGroup8": 0.0,
                    "popGroup9": 0.0,
                    "popGroup10": 0.318464256512099,
                    "popGroup11": 1.514667210175273,
                    "popGroup12": 0.0,
                    "popGroup13": 0.0,
                    "popGroup14": 0.0,
                    "popGroup15": 0.0
                }
            }
        }
    }
}