{
    "Sum_Trips_per_Mode": {
        "work": {
            "60101": {
                "car": 5692.279721935092,
                "publicTransport": 400.1300027267197
            },
            "60669": {
                "car": 704.3087603251131,
                "publicTransport": 89.2786294140505
            },
            "60608": {
                "car": 409.60542609983526,
                "publicTransport": 41.3196701453878
            },
            "60611": {
                "car": 286.7663707220023,
                "publicTransport": 37.99930488062126
            },
            "60670": {
                "car": 1904.4643200743967,
                "publicTransport": 2400.058744846893
            },
            "60662": {
                "car": 166.99564959603407,
                "publicTransport": 18.235346172010612
            },
            "60656": {
                "car": 497.93754937210264,
                "publicTransport": 129.5468732235698
            },
            "60655": {
                "car": 738.887604128899,
                "publicTransport": 71.37397921976712
            },
            "60624": {
                "car": 1495.4555576127393,
                "publicTransport": 289.5982458655511
            },
            "60660": {
                "car": 461.77680637021547,
                "publicTransport": 173.04465342138582
            },
            "60629": {
                "car": 517.3815846588111,
                "publicTransport": 88.02771815695161
            },
            "60618": {
                "car": 246.63427283314638,
                "publicTransport": 71.13866741350732
            },
            "61059": {
                "car": 98.44640853647755,
                "publicTransport": 8.222272661189416
            },
            "61001": {
                "car": 47.94501630267587,
                "publicTransport": 5.0738727049770915
            },
            "61055": {
                "car": 61.66783908008244,
                "publicTransport": 7.568387237252892
            },
            "61021": {
                "car": 115.2134465633923,
                "publicTransport": 6.9126849931784955
            },
            "61017": {
                "car": 23.231863506399783,
                "publicTransport": 1.8003134957839635
            },
            "61020": {
                "car": 35.50331656099951,
                "publicTransport": 2.0550707324543773
            },
            "61012": {
                "car": 62.46949434924183,
                "publicTransport": 4.269252232828366
            },
            "61043": {
                "car": 77.74670651357843,
                "publicTransport": 4.499698729002551
            },
            "61053": {
                "car": 590.0784942514633,
                "publicTransport": 34.087976536999484
            },
            "61027": {
                "car": 76.47625159384089,
                "publicTransport": 2.269356345291484
            },
            "61016": {
                "car": 37.16210147483664,
                "publicTransport": 2.2335517166024506
            },
            "61045": {
                "car": 145.39108218384717,
                "publicTransport": 8.892161594230867
            },
            "61008": {
                "car": 107.17016623109191,
                "publicTransport": 3.690958740584122
            },
            "61050": {
                "car": 46.72172081005236,
                "publicTransport": 5.848296017470539
            },
            "61049": {
                "car": 67.35616633357341,
                "publicTransport": 4.372349813454789
            },
            "61058": {
                "car": 176.09110238814424,
                "publicTransport": 11.05498264462737
            },
            "62347": {
                "car": 24.029786572320273,
                "publicTransport": 1.5719241071611072
            }
        }
    },
    "Trips_per_group": {
        "work": {
            "60101": {
                "car": {
                    "popGroup2": 2901.8719926946587,
                    "popGroup4": 0.0,
                    "popGroup6": 0.0,
                    "popGroup10": 2790.407729240434,
                    "popGroup12": 0.0,
                    "popGroup14": 0.0
                },
                "publicTransport": {
                    "popGroup0": 0.0,
                    "popGroup1": 0.0,
                    "popGroup2": 158.47824262194658,
                    "popGroup3": 45.98905497804479,
                    "popGroup4": 0.0,
                    "popGroup5": 0.0,
                    "popGroup6": 0.0,
                    "popGroup7": 0.0,
                    "popGroup8": 0.0,
                    "popGroup9": 0.0,
                    "popGroup10": 152.4055787833809,
                    "popGroup11": 43.25712634334744,
                    "popGroup12": 0.0,
                    "popGroup13": 0.0,
                    "popGroup14": 0.0,
                    "popGroup15": 0.0
                }
            },
            "60669": {
                "car": {
                    "popGroup2": 359.06746489839753,
                    "popGroup4": 0.0,
                    "popGroup6": 0.0,
                    "popGroup10": 345.2412954267156,
                    "popGroup12": 0.0,
                    "popGroup14": 0.0
                },
                "publicTransport": {
                    "popGroup0": 0.0,
                    "popGroup1": 0.0,
                    "popGroup2": 35.36951899424834,
                    "popGroup3": 10.250897626939016,
                    "popGroup4": 0.0,
                    "popGroup5": 0.0,
                    "popGroup6": 0.0,
                    "popGroup7": 0.0,
                    "popGroup8": 0.0,
                    "popGroup9": 0.0,
                    "popGroup10": 34.005346155761174,
                    "popGroup11": 9.652866637101969,
                    "popGroup12": 0.0,
                    "popGroup13": 0.0,
                    "popGroup14": 0.0,
                    "popGroup15": 0.0
                }
            },
            "60608": {
                "car": {
                    "popGroup2": 208.82714153163744,
                    "popGroup4": 0.0,
                    "popGroup6": 0.0,
                    "popGroup10": 200.77828456819782,
                    "popGroup12": 0.0,
                    "popGroup14": 0.0
                },
                "publicTransport": {
                    "popGroup0": 0.0,
                    "popGroup1": 0.0,
                    "popGroup2": 16.369453326426544,
                    "popGroup3": 4.744476720780993,
                    "popGroup4": 0.0,
                    "popGroup5": 0.0,
                    "popGroup6": 0.0,
                    "popGroup7": 0.0,
                    "popGroup8": 0.0,
                    "popGroup9": 0.0,
                    "popGroup10": 15.738250623595437,
                    "popGroup11": 4.467489474584827,
                    "popGroup12": 0.0,
                    "popGroup13": 0.0,
                    "popGroup14": 0.0,
                    "popGroup15": 0.0
                }
            },
            "60611": {
                "car": {
                    "popGroup2": 146.19825522732754,
                    "popGroup4": 0.0,
                    "popGroup6": 0.0,
                    "popGroup10": 140.56811549467477,
                    "popGroup12": 0.0,
                    "popGroup14": 0.0
                },
                "publicTransport": {
                    "popGroup0": 0.0,
                    "popGroup1": 0.0,
                    "popGroup2": 15.05271020272263,
                    "popGroup3": 4.36461272147022,
                    "popGroup4": 0.0,
                    "popGroup5": 0.0,
                    "popGroup6": 0.0,
                    "popGroup7": 0.0,
                    "popGroup8": 0.0,
                    "popGroup9": 0.0,
                    "popGroup10": 14.473629240785645,
                    "popGroup11": 4.108352715642764,
                    "popGroup12": 0.0,
                    "popGroup13": 0.0,
                    "popGroup14": 0.0,
                    "popGroup15": 0.0
                }
            },
            "60670": {
                "car": {
                    "popGroup2": 970.965955171914,
                    "popGroup4": 0.0,
                    "popGroup6": 0.0,
                    "popGroup10": 933.4983649024828,
                    "popGroup12": 0.0,
                    "popGroup14": 0.0
                },
                "publicTransport": {
                    "popGroup0": 0.0,
                    "popGroup1": 0.0,
                    "popGroup2": 950.8430873936636,
                    "popGroup3": 275.5683279852382,
                    "popGroup4": 0.0,
                    "popGroup5": 0.0,
                    "popGroup6": 0.0,
                    "popGroup7": 0.0,
                    "popGroup8": 0.0,
                    "popGroup9": 0.0,
                    "popGroup10": 914.1523690283241,
                    "popGroup11": 259.4949604396669,
                    "popGroup12": 0.0,
                    "popGroup13": 0.0,
                    "popGroup14": 0.0,
                    "popGroup15": 0.0
                }
            },
            "60662": {
                "car": {
                    "popGroup2": 85.13631505313626,
                    "popGroup4": 0.0,
                    "popGroup6": 0.0,
                    "popGroup10": 81.8593345428978,
                    "popGroup12": 0.0,
                    "popGroup14": 0.0
                },
                "publicTransport": {
                    "popGroup0": 0.0,
                    "popGroup1": 0.0,
                    "popGroup2": 7.223479535773153,
                    "popGroup3": 2.0946108565014545,
                    "popGroup4": 0.0,
                    "popGroup5": 0.0,
                    "popGroup6": 0.0,
                    "popGroup7": 0.0,
                    "popGroup8": 0.0,
                    "popGroup9": 0.0,
                    "popGroup10": 6.945718575069459,
                    "popGroup11": 1.9715372046665463,
                    "popGroup12": 0.0,
                    "popGroup13": 0.0,
                    "popGroup14": 0.0,
                    "popGroup15": 0.0
                }
            },
            "60656": {
                "car": {
                    "popGroup2": 253.866666157218,
                    "popGroup4": 0.0,
                    "popGroup6": 0.0,
                    "popGroup10": 244.07088321488465,
                    "popGroup12": 0.0,
                    "popGroup14": 0.0
                },
                "publicTransport": {
                    "popGroup0": 0.0,
                    "popGroup1": 0.0,
                    "popGroup2": 51.32364717341589,
                    "popGroup3": 14.873445288992912,
                    "popGroup4": 0.0,
                    "popGroup5": 0.0,
                    "popGroup6": 0.0,
                    "popGroup7": 0.0,
                    "popGroup8": 0.0,
                    "popGroup9": 0.0,
                    "popGroup10": 49.34299968529412,
                    "popGroup11": 14.006781075866872,
                    "popGroup12": 0.0,
                    "popGroup13": 0.0,
                    "popGroup14": 0.0,
                    "popGroup15": 0.0
                }
            },
            "60655": {
                "car": {
                    "popGroup2": 376.71367193759676,
                    "popGroup4": 0.0,
                    "popGroup6": 0.0,
                    "popGroup10": 362.17393219130236,
                    "popGroup12": 0.0,
                    "popGroup14": 0.0
                },
                "publicTransport": {
                    "popGroup0": 0.0,
                    "popGroup1": 0.0,
                    "popGroup2": 28.27857514107746,
                    "popGroup3": 8.192708795742348,
                    "popGroup4": 0.0,
                    "popGroup5": 0.0,
                    "popGroup6": 0.0,
                    "popGroup7": 0.0,
                    "popGroup8": 0.0,
                    "popGroup9": 0.0,
                    "popGroup10": 27.185466564356283,
                    "popGroup11": 7.717228718591035,
                    "popGroup12": 0.0,
                    "popGroup13": 0.0,
                    "popGroup14": 0.0,
                    "popGroup15": 0.0
                }
            },
            "60624": {
                "car": {
                    "popGroup2": 762.4372012670367,
                    "popGroup4": 0.0,
                    "popGroup6": 0.0,
                    "popGroup10": 733.0183563457026,
                    "popGroup12": 0.0,
                    "popGroup14": 0.0
                },
                "publicTransport": {
                    "popGroup0": 0.0,
                    "popGroup1": 0.0,
                    "popGroup2": 114.73755664787662,
                    "popGroup3": 33.24385017946024,
                    "popGroup4": 0.0,
                    "popGroup5": 0.0,
                    "popGroup6": 0.0,
                    "popGroup7": 0.0,
                    "popGroup8": 0.0,
                    "popGroup9": 0.0,
                    "popGroup10": 110.30456161206554,
                    "popGroup11": 31.312277426148725,
                    "popGroup12": 0.0,
                    "popGroup13": 0.0,
                    "popGroup14": 0.0,
                    "popGroup15": 0.0
                }
            },
            "60660": {
                "car": {
                    "popGroup2": 235.4305965872215,
                    "popGroup4": 0.0,
                    "popGroup6": 0.0,
                    "popGroup10": 226.34620978299398,
                    "popGroup12": 0.0,
                    "popGroup14": 0.0
                },
                "publicTransport": {
                    "popGroup0": 0.0,
                    "popGroup1": 0.0,
                    "popGroup2": 68.55405310031105,
                    "popGroup3": 19.870142175584544,
                    "popGroup4": 0.0,
                    "popGroup5": 0.0,
                    "popGroup6": 0.0,
                    "popGroup7": 0.0,
                    "popGroup8": 0.0,
                    "popGroup9": 0.0,
                    "popGroup10": 65.91091660403703,
                    "popGroup11": 18.70954154145318,
                    "popGroup12": 0.0,
                    "popGroup13": 0.0,
                    "popGroup14": 0.0,
                    "popGroup15": 0.0
                }
            },
            "60629": {
                "car": {
                    "popGroup2": 263.7800967590693,
                    "popGroup4": 0.0,
                    "popGroup6": 0.0,
                    "popGroup10": 253.60148789974176,
                    "popGroup12": 0.0,
                    "popGroup14": 0.0
                },
                "publicTransport": {
                    "popGroup0": 0.0,
                    "popGroup1": 0.0,
                    "popGroup2": 34.86955324434552,
                    "popGroup3": 10.111783024907552,
                    "popGroup4": 0.0,
                    "popGroup5": 0.0,
                    "popGroup6": 0.0,
                    "popGroup7": 0.0,
                    "popGroup8": 0.0,
                    "popGroup9": 0.0,
                    "popGroup10": 33.529195089341314,
                    "popGroup11": 9.517186798357214,
                    "popGroup12": 0.0,
                    "popGroup13": 0.0,
                    "popGroup14": 0.0,
                    "popGroup15": 0.0
                }
            },
            "60618": {
                "car": {
                    "popGroup2": 125.74322792401983,
                    "popGroup4": 0.0,
                    "popGroup6": 0.0,
                    "popGroup10": 120.89104490912653,
                    "popGroup12": 0.0,
                    "popGroup14": 0.0
                },
                "publicTransport": {
                    "popGroup0": 0.0,
                    "popGroup1": 0.0,
                    "popGroup2": 28.184391188115484,
                    "popGroup3": 8.166731231971916,
                    "popGroup4": 0.0,
                    "popGroup5": 0.0,
                    "popGroup6": 0.0,
                    "popGroup7": 0.0,
                    "popGroup8": 0.0,
                    "popGroup9": 0.0,
                    "popGroup10": 27.09586786935646,
                    "popGroup11": 7.691677124063461,
                    "popGroup12": 0.0,
                    "popGroup13": 0.0,
                    "popGroup14": 0.0,
                    "popGroup15": 0.0
                }
            },
            "61059": {
                "car": {
                    "popGroup2": 50.18818187087248,
                    "popGroup4": 0.0,
                    "popGroup6": 0.0,
                    "popGroup10": 48.25822666560507,
                    "popGroup12": 0.0,
                    "popGroup14": 0.0
                },
                "publicTransport": {
                    "popGroup0": 0.0,
                    "popGroup1": 0.0,
                    "popGroup2": 3.257009715476388,
                    "popGroup3": 0.9445328477688006,
                    "popGroup4": 0.0,
                    "popGroup5": 0.0,
                    "popGroup6": 0.0,
                    "popGroup7": 0.0,
                    "popGroup8": 0.0,
                    "popGroup9": 0.0,
                    "popGroup10": 3.131783441876266,
                    "popGroup11": 0.8889466560679609,
                    "popGroup12": 0.0,
                    "popGroup13": 0.0,
                    "popGroup14": 0.0,
                    "popGroup15": 0.0
                }
            },
            "61001": {
                "car": {
                    "popGroup2": 24.44308140012769,
                    "popGroup4": 0.0,
                    "popGroup6": 0.0,
                    "popGroup10": 23.501934902548182,
                    "popGroup12": 0.0,
                    "popGroup14": 0.0
                },
                "publicTransport": {
                    "popGroup0": 0.0,
                    "popGroup1": 0.0,
                    "popGroup2": 2.0098683247970115,
                    "popGroup3": 0.5828414913058013,
                    "popGroup4": 0.0,
                    "popGroup5": 0.0,
                    "popGroup6": 0.0,
                    "popGroup7": 0.0,
                    "popGroup8": 0.0,
                    "popGroup9": 0.0,
                    "popGroup10": 1.9325991048381788,
                    "popGroup11": 0.5485637840361002,
                    "popGroup12": 0.0,
                    "popGroup13": 0.0,
                    "popGroup14": 0.0,
                    "popGroup15": 0.0
                }
            },
            "61055": {
                "car": {
                    "popGroup2": 31.439661611505812,
                    "popGroup4": 0.0,
                    "popGroup6": 0.0,
                    "popGroup10": 30.228177468576625,
                    "popGroup12": 0.0,
                    "popGroup14": 0.0
                },
                "publicTransport": {
                    "popGroup0": 0.0,
                    "popGroup1": 0.0,
                    "popGroup2": 2.998033845604134,
                    "popGroup3": 0.8693637611546915,
                    "popGroup4": 0.0,
                    "popGroup5": 0.0,
                    "popGroup6": 0.0,
                    "popGroup7": 0.0,
                    "popGroup8": 0.0,
                    "popGroup9": 0.0,
                    "popGroup10": 2.8827301055835486,
                    "popGroup11": 0.8182595249105178,
                    "popGroup12": 0.0,
                    "popGroup13": 0.0,
                    "popGroup14": 0.0,
                    "popGroup15": 0.0
                }
            },
            "61021": {
                "car": {
                    "popGroup2": 58.736151628722695,
                    "popGroup4": 0.0,
                    "popGroup6": 0.0,
                    "popGroup10": 56.4772949346696,
                    "popGroup12": 0.0,
                    "popGroup14": 0.0
                },
                "publicTransport": {
                    "popGroup0": 0.0,
                    "popGroup1": 0.0,
                    "popGroup2": 2.738229176404145,
                    "popGroup3": 0.7941414099493656,
                    "popGroup4": 0.0,
                    "popGroup5": 0.0,
                    "popGroup6": 0.0,
                    "popGroup7": 0.0,
                    "popGroup8": 0.0,
                    "popGroup9": 0.0,
                    "popGroup10": 2.632961552806222,
                    "popGroup11": 0.7473528540187623,
                    "popGroup12": 0.0,
                    "popGroup13": 0.0,
                    "popGroup14": 0.0,
                    "popGroup15": 0.0
                }
            },
            "61017": {
                "car": {
                    "popGroup2": 11.843783467297284,
                    "popGroup4": 0.0,
                    "popGroup6": 0.0,
                    "popGroup10": 11.388080039102501,
                    "popGroup12": 0.0,
                    "popGroup14": 0.0
                },
                "publicTransport": {
                    "popGroup0": 0.0,
                    "popGroup1": 0.0,
                    "popGroup2": 0.7131660154234677,
                    "popGroup3": 0.2067875628426121,
                    "popGroup4": 0.0,
                    "popGroup5": 0.0,
                    "popGroup6": 0.0,
                    "popGroup7": 0.0,
                    "popGroup8": 0.0,
                    "popGroup9": 0.0,
                    "popGroup10": 0.6857182477295644,
                    "popGroup11": 0.19464166978831926,
                    "popGroup12": 0.0,
                    "popGroup13": 0.0,
                    "popGroup14": 0.0,
                    "popGroup15": 0.0
                }
            },
            "61020": {
                "car": {
                    "popGroup2": 18.099796517247032,
                    "popGroup4": 0.0,
                    "popGroup6": 0.0,
                    "popGroup10": 17.403520043752472,
                    "popGroup12": 0.0,
                    "popGroup14": 0.0
                },
                "publicTransport": {
                    "popGroup0": 0.0,
                    "popGroup1": 0.0,
                    "popGroup2": 0.8140648709222789,
                    "popGroup3": 0.23607406723976324,
                    "popGroup4": 0.0,
                    "popGroup5": 0.0,
                    "popGroup6": 0.0,
                    "popGroup7": 0.0,
                    "popGroup8": 0.0,
                    "popGroup9": 0.0,
                    "popGroup10": 0.7827502026706549,
                    "popGroup11": 0.22218159162168044,
                    "popGroup12": 0.0,
                    "popGroup13": 0.0,
                    "popGroup14": 0.0,
                    "popGroup15": 0.0
                }
            },
            "61012": {
                "car": {
                    "popGroup2": 31.847561365356587,
                    "popGroup4": 0.0,
                    "popGroup6": 0.0,
                    "popGroup10": 30.62193298388524,
                    "popGroup12": 0.0,
                    "popGroup14": 0.0
                },
                "publicTransport": {
                    "popGroup0": 0.0,
                    "popGroup1": 0.0,
                    "popGroup2": 1.6911615407914886,
                    "popGroup3": 0.4904235816721641,
                    "popGroup4": 0.0,
                    "popGroup5": 0.0,
                    "popGroup6": 0.0,
                    "popGroup7": 0.0,
                    "popGroup8": 0.0,
                    "popGroup9": 0.0,
                    "popGroup10": 1.6261020068430043,
                    "popGroup11": 0.4615651035217089,
                    "popGroup12": 0.0,
                    "popGroup13": 0.0,
                    "popGroup14": 0.0,
                    "popGroup15": 0.0
                }
            },
            "61043": {
                "car": {
                    "popGroup2": 39.635823709707715,
                    "popGroup4": 0.0,
                    "popGroup6": 0.0,
                    "popGroup10": 38.11088280387072,
                    "popGroup12": 0.0,
                    "popGroup14": 0.0
                },
                "publicTransport": {
                    "popGroup0": 0.0,
                    "popGroup1": 0.0,
                    "popGroup2": 1.782458774689807,
                    "popGroup3": 0.5168845720292992,
                    "popGroup4": 0.0,
                    "popGroup5": 0.0,
                    "popGroup6": 0.0,
                    "popGroup7": 0.0,
                    "popGroup8": 0.0,
                    "popGroup9": 0.0,
                    "popGroup10": 1.7138748661251089,
                    "popGroup11": 0.48648051615833576,
                    "popGroup12": 0.0,
                    "popGroup13": 0.0,
                    "popGroup14": 0.0,
                    "popGroup15": 0.0
                }
            },
            "61053": {
                "car": {
                    "popGroup2": 300.82529320893246,
                    "popGroup4": 0.0,
                    "popGroup6": 0.0,
                    "popGroup10": 289.2532010425309,
                    "popGroup12": 0.0,
                    "popGroup14": 0.0
                },
                "publicTransport": {
                    "popGroup0": 0.0,
                    "popGroup1": 0.0,
                    "popGroup2": 13.503274021909606,
                    "popGroup3": 3.9156723361591776,
                    "popGroup4": 0.0,
                    "popGroup5": 0.0,
                    "popGroup6": 0.0,
                    "popGroup7": 0.0,
                    "popGroup8": 0.0,
                    "popGroup9": 0.0,
                    "popGroup10": 12.983640081603468,
                    "popGroup11": 3.6853900973272324,
                    "popGroup12": 0.0,
                    "popGroup13": 0.0,
                    "popGroup14": 0.0,
                    "popGroup15": 0.0
                }
            },
            "61027": {
                "car": {
                    "popGroup2": 38.98976189829185,
                    "popGroup4": 0.0,
                    "popGroup6": 0.0,
                    "popGroup10": 37.48648969554903,
                    "popGroup12": 0.0,
                    "popGroup14": 0.0
                },
                "publicTransport": {
                    "popGroup0": 0.0,
                    "popGroup1": 0.0,
                    "popGroup2": 0.8989567233206109,
                    "popGroup3": 0.2606829759417058,
                    "popGroup4": 0.0,
                    "popGroup5": 0.0,
                    "popGroup6": 0.0,
                    "popGroup7": 0.0,
                    "popGroup8": 0.0,
                    "popGroup9": 0.0,
                    "popGroup10": 0.8643673954686558,
                    "popGroup11": 0.2453492505605114,
                    "popGroup12": 0.0,
                    "popGroup13": 0.0,
                    "popGroup14": 0.0,
                    "popGroup15": 0.0
                }
            },
            "61016": {
                "car": {
                    "popGroup2": 18.945698344390912,
                    "popGroup4": 0.0,
                    "popGroup6": 0.0,
                    "popGroup10": 18.216403130445727,
                    "popGroup12": 0.0,
                    "popGroup14": 0.0
                },
                "publicTransport": {
                    "popGroup0": 0.0,
                    "popGroup1": 0.0,
                    "popGroup2": 0.8847990760937784,
                    "popGroup3": 0.25654696000540733,
                    "popGroup4": 0.0,
                    "popGroup5": 0.0,
                    "popGroup6": 0.0,
                    "popGroup7": 0.0,
                    "popGroup8": 0.0,
                    "popGroup9": 0.0,
                    "popGroup10": 0.8507258200211276,
                    "popGroup11": 0.24147986048213732,
                    "popGroup12": 0.0,
                    "popGroup13": 0.0,
                    "popGroup14": 0.0,
                    "popGroup15": 0.0
                }
            },
            "61045": {
                "car": {
                    "popGroup2": 74.12146130595505,
                    "popGroup4": 0.0,
                    "popGroup6": 0.0,
                    "popGroup10": 71.26962087789211,
                    "popGroup12": 0.0,
                    "popGroup14": 0.0
                },
                "publicTransport": {
                    "popGroup0": 0.0,
                    "popGroup1": 0.0,
                    "popGroup2": 3.522485162149364,
                    "popGroup3": 1.021409807165687,
                    "popGroup4": 0.0,
                    "popGroup5": 0.0,
                    "popGroup6": 0.0,
                    "popGroup7": 0.0,
                    "popGroup8": 0.0,
                    "popGroup9": 0.0,
                    "popGroup10": 3.3868967255452485,
                    "popGroup11": 0.9613698993705665,
                    "popGroup12": 0.0,
                    "popGroup13": 0.0,
                    "popGroup14": 0.0,
                    "popGroup15": 0.0
                }
            },
            "61008": {
                "car": {
                    "popGroup2": 54.63951156817623,
                    "popGroup4": 0.0,
                    "popGroup6": 0.0,
                    "popGroup10": 52.53065466291569,
                    "popGroup12": 0.0,
                    "popGroup14": 0.0
                },
                "publicTransport": {
                    "popGroup0": 0.0,
                    "popGroup1": 0.0,
                    "popGroup2": 1.4621307166708444,
                    "popGroup3": 0.42395065717657804,
                    "popGroup4": 0.0,
                    "popGroup5": 0.0,
                    "popGroup6": 0.0,
                    "popGroup7": 0.0,
                    "popGroup8": 0.0,
                    "popGroup9": 0.0,
                    "popGroup10": 1.4058307152336844,
                    "popGroup11": 0.39904665150301544,
                    "popGroup12": 0.0,
                    "popGroup13": 0.0,
                    "popGroup14": 0.0,
                    "popGroup15": 0.0
                }
            },
            "61050": {
                "car": {
                    "popGroup2": 23.81897981573986,
                    "popGroup4": 0.0,
                    "popGroup6": 0.0,
                    "popGroup10": 22.902740994312506,
                    "popGroup12": 0.0,
                    "popGroup14": 0.0
                },
                "publicTransport": {
                    "popGroup0": 0.0,
                    "popGroup1": 0.0,
                    "popGroup2": 2.3167443037393998,
                    "popGroup3": 0.6717364302972623,
                    "popGroup4": 0.0,
                    "popGroup5": 0.0,
                    "popGroup6": 0.0,
                    "popGroup7": 0.0,
                    "popGroup8": 0.0,
                    "popGroup9": 0.0,
                    "popGroup10": 2.227527822878929,
                    "popGroup11": 0.6322874605549481,
                    "popGroup12": 0.0,
                    "popGroup13": 0.0,
                    "popGroup14": 0.0,
                    "popGroup15": 0.0
                }
            },
            "61049": {
                "car": {
                    "popGroup2": 34.33884716128638,
                    "popGroup4": 0.0,
                    "popGroup6": 0.0,
                    "popGroup10": 33.01731917228703,
                    "popGroup12": 0.0,
                    "popGroup14": 0.0
                },
                "publicTransport": {
                    "popGroup0": 0.0,
                    "popGroup1": 0.0,
                    "popGroup2": 1.7320578163553946,
                    "popGroup3": 0.5022130845612691,
                    "popGroup4": 0.0,
                    "popGroup5": 0.0,
                    "popGroup6": 0.0,
                    "popGroup7": 0.0,
                    "popGroup8": 0.0,
                    "popGroup9": 0.0,
                    "popGroup10": 1.6653632915238712,
                    "popGroup11": 0.47271562101425413,
                    "popGroup12": 0.0,
                    "popGroup13": 0.0,
                    "popGroup14": 0.0,
                    "popGroup15": 0.0
                }
            },
            "61058": {
                "car": {
                    "popGroup2": 89.77320350568823,
                    "popGroup4": 0.0,
                    "popGroup6": 0.0,
                    "popGroup10": 86.317898882456,
                    "popGroup12": 0.0,
                    "popGroup14": 0.0
                },
                "publicTransport": {
                    "popGroup0": 0.0,
                    "popGroup1": 0.0,
                    "popGroup2": 4.379387064103732,
                    "popGroup3": 1.269724361277608,
                    "popGroup4": 0.0,
                    "popGroup5": 0.0,
                    "popGroup6": 0.0,
                    "popGroup7": 0.0,
                    "popGroup8": 0.0,
                    "popGroup9": 0.0,
                    "popGroup10": 4.21066146153608,
                    "popGroup11": 1.195209757709951,
                    "popGroup12": 0.0,
                    "popGroup13": 0.0,
                    "popGroup14": 0.0,
                    "popGroup15": 0.0
                }
            },
            "62347": {
                "car": {
                    "popGroup2": 12.250729001207194,
                    "popGroup4": 0.0,
                    "popGroup6": 0.0,
                    "popGroup10": 11.779057571113078,
                    "popGroup12": 0.0,
                    "popGroup14": 0.0
                },
                "publicTransport": {
                    "popGroup0": 0.0,
                    "popGroup1": 0.0,
                    "popGroup2": 0.6227172477434475,
                    "popGroup3": 0.18053906949018422,
                    "popGroup4": 0.0,
                    "popGroup5": 0.0,
                    "popGroup6": 0.0,
                    "popGroup7": 0.0,
                    "popGroup8": 0.0,
                    "popGroup9": 0.0,
                    "popGroup10": 0.59871891271059,
                    "popGroup11": 0.16994887721688562,
                    "popGroup12": 0.0,
                    "popGroup13": 0.0,
                    "popGroup14": 0.0,
                    "popGroup15": 0.0
                }
            }
        }
    }
}