{
    "Sum_Trips_per_Mode": {
        "work": {
            "60101": {
                "car": 110.8308277347115,
                "publicTransport": 1486.5121998914765
            },
            "60669": {
                "car": 5.518915528857272,
                "publicTransport": 59.98591088648736
            },
            "60608": {
                "car": 2.217351552186247,
                "publicTransport": 29.020531209139122
            },
            "60611": {
                "car": 17.720896435123677,
                "publicTransport": 16.68262798840138
            },
            "60670": {
                "car": 6.0061849292580245,
                "publicTransport": 50.48932133140946
            },
            "60662": {
                "car": 13.91227944931082,
                "publicTransport": 13.22585503762889
            },
            "60656": {
                "car": 1.2701450108418069,
                "publicTransport": 11.91385571258809
            },
            "60655": {
                "car": 1.7518512329620877,
                "publicTransport": 19.955744767861532
            },
            "60624": {
                "car": 3.811247274265407,
                "publicTransport": 44.75468397433944
            },
            "60660": {
                "car": 1.8158257690915702,
                "publicTransport": 12.651305993354011
            },
            "60629": {
                "car": 4.217199058888838,
                "publicTransport": 19.30573529758231
            },
            "60618": {
                "car": 0.7987648918288206,
                "publicTransport": 4.67573401025325
            },
            "61059": {
                "car": 1.8832569019866636,
                "publicTransport": 21.296615434858843
            },
            "61001": {
                "car": 8.539367077074981,
                "publicTransport": 4.3747300767258865
            },
            "61055": {
                "car": 12.188578102717665,
                "publicTransport": 5.867359857468941
            },
            "61021": {
                "car": 51.718620003220266,
                "publicTransport": 24.199200202553577
            },
            "61017": {
                "car": 0.5421360171531512,
                "publicTransport": 3.335745446776148
            },
            "61020": {
                "car": 12.577730318165612,
                "publicTransport": 6.146093175277474
            },
            "61012": {
                "car": 31.71241035097298,
                "publicTransport": 14.16207924988062
            },
            "61043": {
                "car": 28.350520056813167,
                "publicTransport": 13.277214577588467
            },
            "61053": {
                "car": 56.669387372181134,
                "publicTransport": 102.75191775234663
            },
            "61027": {
                "car": 7.813762423666644,
                "publicTransport": 7.813762423666644
            },
            "61016": {
                "car": 4.806524110927088,
                "publicTransport": 4.985646038538787
            },
            "61045": {
                "car": 45.52751989972627,
                "publicTransport": 25.32244065883972
            },
            "61008": {
                "car": 18.759779117843706,
                "publicTransport": 10.201614956555142
            },
            "61050": {
                "car": 16.95811001235812,
                "publicTransport": 13.258402579165711
            },
            "61049": {
                "car": 13.141556759273257,
                "publicTransport": 10.400976829961238
            },
            "61058": {
                "car": 43.09875380417219,
                "publicTransport": 24.58605053656601
            },
            "62347": {
                "car": 4.9869278212653505,
                "publicTransport": 3.0289982691073156
            }
        }
    },
    "Trips_per_group": {
        "work": {
            "60101": {
                "car": {
                    "popGroup0": 0.0,
                    "popGroup1": 53.99821575974145,
                    "popGroup2": 0.0,
                    "popGroup3": 0.0,
                    "popGroup4": 0.0,
                    "popGroup5": 56.832611974970064,
                    "popGroup6": 0.0,
                    "popGroup7": 0.0
                },
                "publicTransport": {
                    "popGroup0": 0.0,
                    "popGroup1": 724.38964339894,
                    "popGroup2": 0.0,
                    "popGroup3": 0.0,
                    "popGroup4": 0.0,
                    "popGroup5": 762.1225564925363,
                    "popGroup6": 0.0,
                    "popGroup7": 0.0
                }
            },
            "60669": {
                "car": {
                    "popGroup0": 0.0,
                    "popGroup1": 2.688885421336102,
                    "popGroup2": 0.0,
                    "popGroup3": 0.0,
                    "popGroup4": 0.0,
                    "popGroup5": 2.8300301075211705,
                    "popGroup6": 0.0,
                    "popGroup7": 0.0
                },
                "publicTransport": {
                    "popGroup0": 0.0,
                    "popGroup1": 29.230387191647456,
                    "popGroup2": 0.0,
                    "popGroup3": 0.0,
                    "popGroup4": 0.0,
                    "popGroup5": 30.755523694839905,
                    "popGroup6": 0.0,
                    "popGroup7": 0.0
                }
            },
            "60608": {
                "car": {
                    "popGroup0": 0.0,
                    "popGroup1": 1.0803192754757,
                    "popGroup2": 0.0,
                    "popGroup3": 0.0,
                    "popGroup4": 0.0,
                    "popGroup5": 1.137032276710547,
                    "popGroup6": 0.0,
                    "popGroup7": 0.0
                },
                "publicTransport": {
                    "popGroup0": 0.0,
                    "popGroup1": 14.141009916193012,
                    "popGroup2": 0.0,
                    "popGroup3": 0.0,
                    "popGroup4": 0.0,
                    "popGroup5": 14.879521292946109,
                    "popGroup6": 0.0,
                    "popGroup7": 0.0
                }
            },
            "60611": {
                "car": {
                    "popGroup0": 0.0,
                    "popGroup1": 8.634450705559043,
                    "popGroup2": 0.0,
                    "popGroup3": 0.0,
                    "popGroup4": 0.0,
                    "popGroup5": 9.086445729564632,
                    "popGroup6": 0.0,
                    "popGroup7": 0.0
                },
                "publicTransport": {
                    "popGroup0": 0.0,
                    "popGroup1": 8.128934048627228,
                    "popGroup2": 0.0,
                    "popGroup3": 0.0,
                    "popGroup4": 0.0,
                    "popGroup5": 8.553693939774151,
                    "popGroup6": 0.0,
                    "popGroup7": 0.0
                }
            },
            "60670": {
                "car": {
                    "popGroup0": 0.0,
                    "popGroup1": 2.926293323966073,
                    "popGroup2": 0.0,
                    "popGroup3": 0.0,
                    "popGroup4": 0.0,
                    "popGroup5": 3.079891605291951,
                    "popGroup6": 0.0,
                    "popGroup7": 0.0
                },
                "publicTransport": {
                    "popGroup0": 0.0,
                    "popGroup1": 24.602237239009384,
                    "popGroup2": 0.0,
                    "popGroup3": 0.0,
                    "popGroup4": 0.0,
                    "popGroup5": 25.887084092400077,
                    "popGroup6": 0.0,
                    "popGroup7": 0.0
                }
            },
            "60662": {
                "car": {
                    "popGroup0": 0.0,
                    "popGroup1": 6.778543340803295,
                    "popGroup2": 0.0,
                    "popGroup3": 0.0,
                    "popGroup4": 0.0,
                    "popGroup5": 7.133736108507524,
                    "popGroup6": 0.0,
                    "popGroup7": 0.0
                },
                "publicTransport": {
                    "popGroup0": 0.0,
                    "popGroup1": 6.444268995592762,
                    "popGroup2": 0.0,
                    "popGroup3": 0.0,
                    "popGroup4": 0.0,
                    "popGroup5": 6.7815860420361265,
                    "popGroup6": 0.0,
                    "popGroup7": 0.0
                }
            },
            "60656": {
                "car": {
                    "popGroup0": 0.0,
                    "popGroup1": 0.6188268081465528,
                    "popGroup2": 0.0,
                    "popGroup3": 0.0,
                    "popGroup4": 0.0,
                    "popGroup5": 0.6513182026952542,
                    "popGroup6": 0.0,
                    "popGroup7": 0.0
                },
                "publicTransport": {
                    "popGroup0": 0.0,
                    "popGroup1": 5.805068071955002,
                    "popGroup2": 0.0,
                    "popGroup3": 0.0,
                    "popGroup4": 0.0,
                    "popGroup5": 6.108787640633087,
                    "popGroup6": 0.0,
                    "popGroup7": 0.0
                }
            },
            "60655": {
                "car": {
                    "popGroup0": 0.0,
                    "popGroup1": 0.8535196565544356,
                    "popGroup2": 0.0,
                    "popGroup3": 0.0,
                    "popGroup4": 0.0,
                    "popGroup5": 0.8983315764076519,
                    "popGroup6": 0.0,
                    "popGroup7": 0.0
                },
                "publicTransport": {
                    "popGroup0": 0.0,
                    "popGroup1": 9.723325770419974,
                    "popGroup2": 0.0,
                    "popGroup3": 0.0,
                    "popGroup4": 0.0,
                    "popGroup5": 10.23241899744156,
                    "popGroup6": 0.0,
                    "popGroup7": 0.0
                }
            },
            "60624": {
                "car": {
                    "popGroup0": 0.0,
                    "popGroup1": 1.8568808381831987,
                    "popGroup2": 0.0,
                    "popGroup3": 0.0,
                    "popGroup4": 0.0,
                    "popGroup5": 1.9543664360822084,
                    "popGroup6": 0.0,
                    "popGroup7": 0.0
                },
                "publicTransport": {
                    "popGroup0": 0.0,
                    "popGroup1": 21.807044302499868,
                    "popGroup2": 0.0,
                    "popGroup3": 0.0,
                    "popGroup4": 0.0,
                    "popGroup5": 22.947639671839575,
                    "popGroup6": 0.0,
                    "popGroup7": 0.0
                }
            },
            "60660": {
                "car": {
                    "popGroup0": 0.0,
                    "popGroup1": 0.8846901781180009,
                    "popGroup2": 0.0,
                    "popGroup3": 0.0,
                    "popGroup4": 0.0,
                    "popGroup5": 0.9311355909735692,
                    "popGroup6": 0.0,
                    "popGroup7": 0.0
                },
                "publicTransport": {
                    "popGroup0": 0.0,
                    "popGroup1": 6.164568701112534,
                    "popGroup2": 0.0,
                    "popGroup3": 0.0,
                    "popGroup4": 0.0,
                    "popGroup5": 6.486737292241477,
                    "popGroup6": 0.0,
                    "popGroup7": 0.0
                }
            },
            "60629": {
                "car": {
                    "popGroup0": 0.0,
                    "popGroup1": 2.0546822210346116,
                    "popGroup2": 0.0,
                    "popGroup3": 0.0,
                    "popGroup4": 0.0,
                    "popGroup5": 2.1625168378542265,
                    "popGroup6": 0.0,
                    "popGroup7": 0.0
                },
                "publicTransport": {
                    "popGroup0": 0.0,
                    "popGroup1": 9.407638082925013,
                    "popGroup2": 0.0,
                    "popGroup3": 0.0,
                    "popGroup4": 0.0,
                    "popGroup5": 9.898097214657296,
                    "popGroup6": 0.0,
                    "popGroup7": 0.0
                }
            },
            "60618": {
                "car": {
                    "popGroup0": 0.0,
                    "popGroup1": 0.38917278289008306,
                    "popGroup2": 0.0,
                    "popGroup3": 0.0,
                    "popGroup4": 0.0,
                    "popGroup5": 0.4095921089387376,
                    "popGroup6": 0.0,
                    "popGroup7": 0.0
                },
                "publicTransport": {
                    "popGroup0": 0.0,
                    "popGroup1": 2.2785237097703748,
                    "popGroup2": 0.0,
                    "popGroup3": 0.0,
                    "popGroup4": 0.0,
                    "popGroup5": 2.3972103004828753,
                    "popGroup6": 0.0,
                    "popGroup7": 0.0
                }
            },
            "61059": {
                "car": {
                    "popGroup0": 0.0,
                    "popGroup1": 0.9175395917531186,
                    "popGroup2": 0.0,
                    "popGroup3": 0.0,
                    "popGroup4": 0.0,
                    "popGroup5": 0.965717310233545,
                    "popGroup6": 0.0,
                    "popGroup7": 0.0
                },
                "publicTransport": {
                    "popGroup0": 0.0,
                    "popGroup1": 10.376253877318344,
                    "popGroup2": 0.0,
                    "popGroup3": 0.0,
                    "popGroup4": 0.0,
                    "popGroup5": 10.920361557540499,
                    "popGroup6": 0.0,
                    "popGroup7": 0.0
                }
            },
            "61001": {
                "car": {
                    "popGroup0": 0.0,
                    "popGroup1": 4.16065120665643,
                    "popGroup2": 0.0,
                    "popGroup3": 0.0,
                    "popGroup4": 0.0,
                    "popGroup5": 4.378715870418552,
                    "popGroup6": 0.0,
                    "popGroup7": 0.0
                },
                "publicTransport": {
                    "popGroup0": 0.0,
                    "popGroup1": 2.1314800025241207,
                    "popGroup2": 0.0,
                    "popGroup3": 0.0,
                    "popGroup4": 0.0,
                    "popGroup5": 2.243250074201766,
                    "popGroup6": 0.0,
                    "popGroup7": 0.0
                }
            },
            "61055": {
                "car": {
                    "popGroup0": 0.0,
                    "popGroup1": 5.938479720787454,
                    "popGroup2": 0.0,
                    "popGroup3": 0.0,
                    "popGroup4": 0.0,
                    "popGroup5": 6.250098381930211,
                    "popGroup6": 0.0,
                    "popGroup7": 0.0
                },
                "publicTransport": {
                    "popGroup0": 0.0,
                    "popGroup1": 2.8586572826728815,
                    "popGroup2": 0.0,
                    "popGroup3": 0.0,
                    "popGroup4": 0.0,
                    "popGroup5": 3.008702574796059,
                    "popGroup6": 0.0,
                    "popGroup7": 0.0
                }
            },
            "61021": {
                "car": {
                    "popGroup0": 0.0,
                    "popGroup1": 25.198479573702325,
                    "popGroup2": 0.0,
                    "popGroup3": 0.0,
                    "popGroup4": 0.0,
                    "popGroup5": 26.520140429517937,
                    "popGroup6": 0.0,
                    "popGroup7": 0.0
                },
                "publicTransport": {
                    "popGroup0": 0.0,
                    "popGroup1": 11.790267598458346,
                    "popGroup2": 0.0,
                    "popGroup3": 0.0,
                    "popGroup4": 0.0,
                    "popGroup5": 12.40893260409523,
                    "popGroup6": 0.0,
                    "popGroup7": 0.0
                }
            },
            "61017": {
                "car": {
                    "popGroup0": 0.0,
                    "popGroup1": 0.26413501875239886,
                    "popGroup2": 0.0,
                    "popGroup3": 0.0,
                    "popGroup4": 0.0,
                    "popGroup5": 0.2780009984007523,
                    "popGroup6": 0.0,
                    "popGroup7": 0.0
                },
                "publicTransport": {
                    "popGroup0": 0.0,
                    "popGroup1": 1.625323436609342,
                    "popGroup2": 0.0,
                    "popGroup3": 0.0,
                    "popGroup4": 0.0,
                    "popGroup5": 1.7104220101668055,
                    "popGroup6": 0.0,
                    "popGroup7": 0.0
                }
            },
            "61020": {
                "car": {
                    "popGroup0": 0.0,
                    "popGroup1": 6.128285617486867,
                    "popGroup2": 0.0,
                    "popGroup3": 0.0,
                    "popGroup4": 0.0,
                    "popGroup5": 6.449444700678745,
                    "popGroup6": 0.0,
                    "popGroup7": 0.0
                },
                "publicTransport": {
                    "popGroup0": 0.0,
                    "popGroup1": 2.9945332550799,
                    "popGroup2": 0.0,
                    "popGroup3": 0.0,
                    "popGroup4": 0.0,
                    "popGroup5": 3.151559920197574,
                    "popGroup6": 0.0,
                    "popGroup7": 0.0
                }
            },
            "61012": {
                "car": {
                    "popGroup0": 0.0,
                    "popGroup1": 15.450841404353454,
                    "popGroup2": 0.0,
                    "popGroup3": 0.0,
                    "popGroup4": 0.0,
                    "popGroup5": 16.261568946619526,
                    "popGroup6": 0.0,
                    "popGroup7": 0.0
                },
                "publicTransport": {
                    "popGroup0": 0.0,
                    "popGroup1": 6.8999570452332755,
                    "popGroup2": 0.0,
                    "popGroup3": 0.0,
                    "popGroup4": 0.0,
                    "popGroup5": 7.262122204647343,
                    "popGroup6": 0.0,
                    "popGroup7": 0.0
                }
            },
            "61043": {
                "car": {
                    "popGroup0": 0.0,
                    "popGroup1": 13.81316173636586,
                    "popGroup2": 0.0,
                    "popGroup3": 0.0,
                    "popGroup4": 0.0,
                    "popGroup5": 14.537358320447305,
                    "popGroup6": 0.0,
                    "popGroup7": 0.0
                },
                "publicTransport": {
                    "popGroup0": 0.0,
                    "popGroup1": 6.468937207263417,
                    "popGroup2": 0.0,
                    "popGroup3": 0.0,
                    "popGroup4": 0.0,
                    "popGroup5": 6.80827737032505,
                    "popGroup6": 0.0,
                    "popGroup7": 0.0
                }
            },
            "61053": {
                "car": {
                    "popGroup0": 0.0,
                    "popGroup1": 27.610014020093914,
                    "popGroup2": 0.0,
                    "popGroup3": 0.0,
                    "popGroup4": 0.0,
                    "popGroup5": 29.059373352087224,
                    "popGroup6": 0.0,
                    "popGroup7": 0.0
                },
                "publicTransport": {
                    "popGroup0": 0.0,
                    "popGroup1": 50.06267435152152,
                    "popGroup2": 0.0,
                    "popGroup3": 0.0,
                    "popGroup4": 0.0,
                    "popGroup5": 52.6892434008251,
                    "popGroup6": 0.0,
                    "popGroup7": 0.0
                }
            },
            "61027": {
                "car": {
                    "popGroup0": 0.0,
                    "popGroup1": 3.806923680965755,
                    "popGroup2": 0.0,
                    "popGroup3": 0.0,
                    "popGroup4": 0.0,
                    "popGroup5": 4.0068387427008885,
                    "popGroup6": 0.0,
                    "popGroup7": 0.0
                },
                "publicTransport": {
                    "popGroup0": 0.0,
                    "popGroup1": 3.806923680965755,
                    "popGroup2": 0.0,
                    "popGroup3": 0.0,
                    "popGroup4": 0.0,
                    "popGroup5": 4.0068387427008885,
                    "popGroup6": 0.0,
                    "popGroup7": 0.0
                }
            },
            "61016": {
                "car": {
                    "popGroup0": 0.0,
                    "popGroup1": 2.3418774338491066,
                    "popGroup2": 0.0,
                    "popGroup3": 0.0,
                    "popGroup4": 0.0,
                    "popGroup5": 2.464646677077982,
                    "popGroup6": 0.0,
                    "popGroup7": 0.0
                },
                "publicTransport": {
                    "popGroup0": 0.0,
                    "popGroup1": 2.4292122614089027,
                    "popGroup2": 0.0,
                    "popGroup3": 0.0,
                    "popGroup4": 0.0,
                    "popGroup5": 2.556433777129885,
                    "popGroup6": 0.0,
                    "popGroup7": 0.0
                }
            },
            "61045": {
                "car": {
                    "popGroup0": 0.0,
                    "popGroup1": 22.18236780156614,
                    "popGroup2": 0.0,
                    "popGroup3": 0.0,
                    "popGroup4": 0.0,
                    "popGroup5": 23.345152098160128,
                    "popGroup6": 0.0,
                    "popGroup7": 0.0
                },
                "publicTransport": {
                    "popGroup0": 0.0,
                    "popGroup1": 12.337738542217842,
                    "popGroup2": 0.0,
                    "popGroup3": 0.0,
                    "popGroup4": 0.0,
                    "popGroup5": 12.984702116621879,
                    "popGroup6": 0.0,
                    "popGroup7": 0.0
                }
            },
            "61008": {
                "car": {
                    "popGroup0": 0.0,
                    "popGroup1": 9.140194877665685,
                    "popGroup2": 0.0,
                    "popGroup3": 0.0,
                    "popGroup4": 0.0,
                    "popGroup5": 9.619584240178023,
                    "popGroup6": 0.0,
                    "popGroup7": 0.0
                },
                "publicTransport": {
                    "popGroup0": 0.0,
                    "popGroup1": 4.970423302309539,
                    "popGroup2": 0.0,
                    "popGroup3": 0.0,
                    "popGroup4": 0.0,
                    "popGroup5": 5.2311916542456025,
                    "popGroup6": 0.0,
                    "popGroup7": 0.0
                }
            },
            "61050": {
                "car": {
                    "popGroup0": 0.0,
                    "popGroup1": 8.262745240316852,
                    "popGroup2": 0.0,
                    "popGroup3": 0.0,
                    "popGroup4": 0.0,
                    "popGroup5": 8.695364772041266,
                    "popGroup6": 0.0,
                    "popGroup7": 0.0
                },
                "publicTransport": {
                    "popGroup0": 0.0,
                    "popGroup1": 6.4599450371343625,
                    "popGroup2": 0.0,
                    "popGroup3": 0.0,
                    "popGroup4": 0.0,
                    "popGroup5": 6.798457542031349,
                    "popGroup6": 0.0,
                    "popGroup7": 0.0
                }
            },
            "61049": {
                "car": {
                    "popGroup0": 0.0,
                    "popGroup1": 6.4030910388577045,
                    "popGroup2": 0.0,
                    "popGroup3": 0.0,
                    "popGroup4": 0.0,
                    "popGroup5": 6.738465720415553,
                    "popGroup6": 0.0,
                    "popGroup7": 0.0
                },
                "publicTransport": {
                    "popGroup0": 0.0,
                    "popGroup1": 5.06766346044113,
                    "popGroup2": 0.0,
                    "popGroup3": 0.0,
                    "popGroup4": 0.0,
                    "popGroup5": 5.3333133695201065,
                    "popGroup6": 0.0,
                    "popGroup7": 0.0
                }
            },
            "61058": {
                "car": {
                    "popGroup0": 0.0,
                    "popGroup1": 20.99947132608196,
                    "popGroup2": 0.0,
                    "popGroup3": 0.0,
                    "popGroup4": 0.0,
                    "popGroup5": 22.09928247809023,
                    "popGroup6": 0.0,
                    "popGroup7": 0.0
                },
                "publicTransport": {
                    "popGroup0": 0.0,
                    "popGroup1": 11.979212655641454,
                    "popGroup2": 0.0,
                    "popGroup3": 0.0,
                    "popGroup4": 0.0,
                    "popGroup5": 12.606837880924555,
                    "popGroup6": 0.0,
                    "popGroup7": 0.0
                }
            },
            "62347": {
                "car": {
                    "popGroup0": 0.0,
                    "popGroup1": 2.4298790135332204,
                    "popGroup2": 0.0,
                    "popGroup3": 0.0,
                    "popGroup4": 0.0,
                    "popGroup5": 2.55704880773213,
                    "popGroup6": 0.0,
                    "popGroup7": 0.0
                },
                "publicTransport": {
                    "popGroup0": 0.0,
                    "popGroup1": 1.4758727944451957,
                    "popGroup2": 0.0,
                    "popGroup3": 0.0,
                    "popGroup4": 0.0,
                    "popGroup5": 1.55312547466212,
                    "popGroup6": 0.0,
                    "popGroup7": 0.0
                }
            }
        }
    }
}